zfb3_1/__init__.py
zfb3_1-1.0.6.dist-info/METADATA
zfb3_1-1.0.6.dist-info/WHEEL
zfb3_1-1.0.6.dist-info/top_level.txt
zfb3_1-1.0.6.dist-info/RECORD
