Metadata-Version: 2.4
Name: zfb3_1
Version: 1.0.6
Summary: print(函数)
Author: Gtl
Author-email: vvvmcvvv@163.com
Dynamic: author
Dynamic: author-email
Dynamic: summary
